{
  "id": 76317867,
  "title": "12.03.2026 – Langsam Gesprochene Nachrichten",
  "date": "2026-03-12",
  "audioUrl": "https://radiodownloaddw-a.akamaihd.net/Events/dwelle/dira/mp3/deutschkurse/langsamenachrichten/CA7AEFD6_2.mp3",
  "duration": 448,
  "imageUrl": "https://static.dw.com/image/76316883_303.jpg",
  "paragraphs": [
    {
      "isHeadline": true,
      "text": "Lufthansa will trotz Streik 60 Prozent aller Langstreckenflüge durchführen",
      "words": [
        {
          "word": "Lufthansa",
          "start": 17.42,
          "end": 18.5,
          "translation": "Lufthansa"
        },
        {
          "word": "will",
          "start": 18.5,
          "end": 18.9,
          "translation": "wants"
        },
        {
          "word": "trotz",
          "start": 18.9,
          "end": 19.56,
          "translation": "despite"
        },
        {
          "word": "Streik",
          "start": 19.56,
          "end": 20.18,
          "translation": "Strike"
        },
        {
          "word": "60",
          "start": 20.18,
          "end": 20.88,
          "translation": "60"
        },
        {
          "word": "Prozent",
          "start": 20.88,
          "end": 21.48,
          "translation": "Percent"
        },
        {
          "word": "aller",
          "start": 21.48,
          "end": 22.12,
          "translation": "all"
        },
        {
          "word": "Langstreckenflüge",
          "start": 22.12,
          "end": 23.54,
          "translation": "Long-haul flights"
        },
        {
          "word": "durchführen",
          "start": 23.54,
          "end": 24.46,
          "translation": "carry out"
        }
      ]
    },
    {
      "isHeadline": false,
      "text": "Piloten der Lufthansa haben ihre Arbeit niedergelegt. Von dem zweitägigen Streik betroffen ist auch die Tochtergesellschaft Cityline. Trotzdem will Deutschlands größte Fluggesellschaft an diesem Donnerstag und Freitag mehr als die Hälfte ihres Flugprogramms aufrechterhalten. Bei Langstreckenverbindungen liege der Anteil „bei 60 Prozent“, teilte die Airline in Frankfurt am Main mit. Die Frachtsparte Lufthansa Cargo muss demnach 20 Prozent ihrer geplanten Flüge an den beiden Streiktagen absagen. Den Piloten geht es in ihrem Arbeitskampf unter anderem um eine bessere Altersvorsorge.",
      "words": [
        {
          "word": "Piloten",
          "start": 25.56,
          "end": 26.14,
          "translation": "Pilots"
        },
        {
          "word": "der",
          "start": 26.14,
          "end": 26.36,
          "translation": "the"
        },
        {
          "word": "Lufthansa",
          "start": 26.36,
          "end": 27.12,
          "translation": "Lufthansa"
        },
        {
          "word": "haben",
          "start": 27.12,
          "end": 27.58,
          "translation": "have"
        },
        {
          "word": "ihre",
          "start": 27.58,
          "end": 27.98,
          "translation": "their"
        },
        {
          "word": "Arbeit",
          "start": 27.98,
          "end": 28.42,
          "translation": "Work"
        },
        {
          "word": "niedergelegt.",
          "start": 28.42,
          "end": 29.44,
          "translation": "laid down."
        },
        {
          "word": "Von",
          "start": 29.74,
          "end": 30.38,
          "translation": "From"
        },
        {
          "word": "dem",
          "start": 30.38,
          "end": 30.66,
          "translation": "the"
        },
        {
          "word": "zweitägigen",
          "start": 30.66,
          "end": 31.7,
          "translation": "two-day"
        },
        {
          "word": "Streik",
          "start": 31.7,
          "end": 32.28,
          "translation": "Strike"
        },
        {
          "word": "betroffen",
          "start": 32.28,
          "end": 32.9,
          "translation": "affected"
        },
        {
          "word": "ist",
          "start": 32.9,
          "end": 33.48,
          "translation": "is"
        },
        {
          "word": "auch",
          "start": 33.48,
          "end": 33.86,
          "translation": "also"
        },
        {
          "word": "die",
          "start": 33.86,
          "end": 34.14,
          "translation": "the"
        },
        {
          "word": "Tochtergesellschaft",
          "start": 34.14,
          "end": 35.32,
          "translation": "Subsidiary"
        },
        {
          "word": "Cityline.",
          "start": 35.32,
          "end": 36.62,
          "translation": "Cityline."
        },
        {
          "word": "Trotzdem",
          "start": 37.44,
          "end": 38.08,
          "translation": "Nevertheless"
        },
        {
          "word": "will",
          "start": 38.08,
          "end": 38.5,
          "translation": "wants"
        },
        {
          "word": "Deutschlands",
          "start": 38.5,
          "end": 39.46,
          "translation": "Germany"
        },
        {
          "word": "größte",
          "start": 39.46,
          "end": 39.94,
          "translation": "largest"
        },
        {
          "word": "Fluggesellschaft",
          "start": 39.94,
          "end": 41.06,
          "translation": "Airline"
        },
        {
          "word": "an",
          "start": 41.06,
          "end": 41.5,
          "translation": "on"
        },
        {
          "word": "diesem",
          "start": 41.5,
          "end": 41.92,
          "translation": "this"
        },
        {
          "word": "Donnerstag",
          "start": 41.92,
          "end": 42.72,
          "translation": "Thursday"
        },
        {
          "word": "und",
          "start": 42.72,
          "end": 43.22,
          "translation": "and"
        },
        {
          "word": "Freitag",
          "start": 43.22,
          "end": 44.14,
          "translation": "Friday"
        },
        {
          "word": "mehr",
          "start": 44.14,
          "end": 44.8,
          "translation": "more"
        },
        {
          "word": "als",
          "start": 44.8,
          "end": 45.24,
          "translation": "as"
        },
        {
          "word": "die",
          "start": 45.24,
          "end": 45.46,
          "translation": "the"
        },
        {
          "word": "Hälfte",
          "start": 45.46,
          "end": 45.98,
          "translation": "Half"
        },
        {
          "word": "ihres",
          "start": 45.98,
          "end": 46.52,
          "translation": "their"
        },
        {
          "word": "Flugprogramms",
          "start": 46.52,
          "end": 47.88,
          "translation": "Flight program"
        },
        {
          "word": "aufrechterhalten.",
          "start": 47.88,
          "end": 50.26,
          "translation": "maintained."
        },
        {
          "word": "Bei",
          "start": 50.26,
          "end": 50.74,
          "translation": "With"
        },
        {
          "word": "Langstreckenverbindungen",
          "start": 50.74,
          "end": 51.85,
          "translation": "Long-haul connections"
        },
        {
          "word": "liege",
          "start": 51.85,
          "end": 52.96,
          "translation": "lie"
        },
        {
          "word": "der",
          "start": 52.96,
          "end": 53.36,
          "translation": "the"
        },
        {
          "word": "Anteil",
          "start": 53.36,
          "end": 54.08,
          "translation": "Share"
        },
        {
          "word": "„bei",
          "start": 54.08,
          "end": 54.64,
          "translation": "\"at"
        },
        {
          "word": "60",
          "start": 54.64,
          "end": 55.28,
          "translation": "60"
        },
        {
          "word": "Prozent“,",
          "start": 55.28,
          "end": 56.0,
          "translation": "percent\","
        },
        {
          "word": "teilte",
          "start": 56.0,
          "end": 57.14,
          "translation": "shared"
        },
        {
          "word": "die",
          "start": 57.14,
          "end": 57.34,
          "translation": "the"
        },
        {
          "word": "Airline",
          "start": 57.34,
          "end": 57.98,
          "translation": "Airline"
        },
        {
          "word": "in",
          "start": 57.98,
          "end": 58.18,
          "translation": "in"
        },
        {
          "word": "Frankfurt",
          "start": 58.18,
          "end": 58.76,
          "translation": "Frankfurt"
        },
        {
          "word": "am",
          "start": 58.76,
          "end": 59.14,
          "translation": "on"
        },
        {
          "word": "Main",
          "start": 59.14,
          "end": 59.5,
          "translation": "Main"
        },
        {
          "word": "mit.",
          "start": 59.5,
          "end": 60.0,
          "translation": "with."
        },
        {
          "word": "Die",
          "start": 60.66,
          "end": 61.02,
          "translation": "The"
        },
        {
          "word": "Frachtsparte",
          "start": 61.02,
          "end": 62.14,
          "translation": "Freight division"
        },
        {
          "word": "Lufthansa",
          "start": 62.14,
          "end": 63.12,
          "translation": "Lufthansa"
        },
        {
          "word": "Cargo",
          "start": 63.12,
          "end": 63.8,
          "translation": "Cargo"
        },
        {
          "word": "muss",
          "start": 63.8,
          "end": 64.6,
          "translation": "must"
        },
        {
          "word": "demnach",
          "start": 64.6,
          "end": 65.4,
          "translation": "therefore"
        },
        {
          "word": "20",
          "start": 65.4,
          "end": 66.06,
          "translation": "20"
        },
        {
          "word": "Prozent",
          "start": 66.06,
          "end": 66.68,
          "translation": "Percent"
        },
        {
          "word": "ihrer",
          "start": 66.68,
          "end": 67.3,
          "translation": "their"
        },
        {
          "word": "geplanten",
          "start": 67.3,
          "end": 68.24,
          "translation": "planned"
        },
        {
          "word": "Flüge",
          "start": 68.24,
          "end": 68.74,
          "translation": "Flights"
        },
        {
          "word": "an",
          "start": 68.74,
          "end": 69.26,
          "translation": "on"
        },
        {
          "word": "den",
          "start": 69.26,
          "end": 69.44,
          "translation": "the"
        },
        {
          "word": "beiden",
          "start": 69.44,
          "end": 69.86,
          "translation": "both"
        },
        {
          "word": "Streiktagen",
          "start": 69.86,
          "end": 70.92,
          "translation": "strike days"
        },
        {
          "word": "absagen.",
          "start": 70.92,
          "end": 71.76,
          "translation": "cancel."
        },
        {
          "word": "Den",
          "start": 72.58,
          "end": 72.78,
          "translation": "The"
        },
        {
          "word": "Piloten",
          "start": 72.78,
          "end": 73.54,
          "translation": "Pilots"
        },
        {
          "word": "geht",
          "start": 73.54,
          "end": 73.9,
          "translation": "goes"
        },
        {
          "word": "es",
          "start": 73.9,
          "end": 74.24,
          "translation": "it"
        },
        {
          "word": "in",
          "start": 74.24,
          "end": 74.38,
          "translation": "in"
        },
        {
          "word": "ihrem",
          "start": 74.38,
          "end": 74.72,
          "translation": "their"
        },
        {
          "word": "Arbeitskampf",
          "start": 74.72,
          "end": 75.72,
          "translation": "Labor dispute"
        },
        {
          "word": "unter",
          "start": 75.72,
          "end": 76.16,
          "translation": "under"
        },
        {
          "word": "anderem",
          "start": 76.16,
          "end": 76.8,
          "translation": "other"
        },
        {
          "word": "um",
          "start": 76.8,
          "end": 77.32,
          "translation": "to"
        },
        {
          "word": "eine",
          "start": 77.32,
          "end": 77.76,
          "translation": "one"
        },
        {
          "word": "bessere",
          "start": 77.76,
          "end": 78.44,
          "translation": "better"
        },
        {
          "word": "Altersvorsorge.",
          "start": 78.44,
          "end": 79.88,
          "translation": "Retirement provision."
        }
      ]
    },
    {
      "isHeadline": true,
      "text": "UN-Sicherheitsrat verurteilt Irans Attacken auf Nachbarstaaten",
      "words": [
        {
          "word": "UN-Sicherheitsrat",
          "start": 79.88,
          "end": 83.96,
          "translation": "UN Security Council"
        },
        {
          "word": "verurteilt",
          "start": 83.96,
          "end": 85.04,
          "translation": "condemned"
        },
        {
          "word": "Irans",
          "start": 85.04,
          "end": 85.8,
          "translation": "Iran's"
        },
        {
          "word": "Attacken",
          "start": 85.8,
          "end": 86.32,
          "translation": "Attacks"
        },
        {
          "word": "auf",
          "start": 86.32,
          "end": 86.82,
          "translation": "on"
        },
        {
          "word": "Nachbarstaaten",
          "start": 86.82,
          "end": 88.82,
          "translation": "Neighboring countries"
        }
      ]
    },
    {
      "isHeadline": false,
      "text": "Das höchste Gremium der Vereinten Nationen hat das sofortige Ende der iranischen Angriffe auf die umliegenden Golfstaaten gefordert. 13 der 15 Mitglieder des UN-Sicherheitsrates stimmten in New York für eine entsprechende Resolution. Die Veto-Mächte Russland und China enthielten sich. Seit Beginn des Krieges Ende Februar sehen sich die Golfstaaten Raketen- und Drohnenattacken aus dem Iran ausgesetzt. Diese Angriffe seien völkerrechtswidrig und stellten eine „ernste Bedrohung für den weltweiten Frieden und die Sicherheit“ dar, heißt es in der Resolution.",
      "words": [
        {
          "word": "Das",
          "start": 88.82,
          "end": 89.6,
          "translation": "The"
        },
        {
          "word": "höchste",
          "start": 89.6,
          "end": 90.26,
          "translation": "highest"
        },
        {
          "word": "Gremium",
          "start": 90.26,
          "end": 90.94,
          "translation": "Board"
        },
        {
          "word": "der",
          "start": 90.94,
          "end": 91.32,
          "translation": "the"
        },
        {
          "word": "Vereinten",
          "start": 91.32,
          "end": 92.22,
          "translation": "United"
        },
        {
          "word": "Nationen",
          "start": 92.22,
          "end": 93.38,
          "translation": "Nations"
        },
        {
          "word": "hat",
          "start": 93.38,
          "end": 93.64,
          "translation": "has"
        },
        {
          "word": "das",
          "start": 93.64,
          "end": 93.94,
          "translation": "the"
        },
        {
          "word": "sofortige",
          "start": 93.94,
          "end": 94.92,
          "translation": "immediate"
        },
        {
          "word": "Ende",
          "start": 94.92,
          "end": 95.32,
          "translation": "End"
        },
        {
          "word": "der",
          "start": 95.32,
          "end": 95.8,
          "translation": "the"
        },
        {
          "word": "iranischen",
          "start": 95.8,
          "end": 96.76,
          "translation": "Iranian"
        },
        {
          "word": "Angriffe",
          "start": 96.76,
          "end": 97.5,
          "translation": "Attacks"
        },
        {
          "word": "auf",
          "start": 97.5,
          "end": 98.12,
          "translation": "on"
        },
        {
          "word": "die",
          "start": 98.12,
          "end": 98.42,
          "translation": "the"
        },
        {
          "word": "umliegenden",
          "start": 98.42,
          "end": 99.38,
          "translation": "surrounding"
        },
        {
          "word": "Golfstaaten",
          "start": 99.38,
          "end": 100.44,
          "translation": "Gulf States"
        },
        {
          "word": "gefordert.",
          "start": 100.44,
          "end": 101.28,
          "translation": "required."
        },
        {
          "word": "13",
          "start": 102.02,
          "end": 102.82,
          "translation": "13"
        },
        {
          "word": "der",
          "start": 102.82,
          "end": 103.2,
          "translation": "the"
        },
        {
          "word": "15",
          "start": 103.2,
          "end": 103.84,
          "translation": "15"
        },
        {
          "word": "Mitglieder",
          "start": 103.84,
          "end": 104.8,
          "translation": "Members"
        },
        {
          "word": "des",
          "start": 104.8,
          "end": 105.16,
          "translation": "of the"
        },
        {
          "word": "UN-Sicherheitsrates",
          "start": 105.16,
          "end": 107.24,
          "translation": "UN Security Council"
        },
        {
          "word": "stimmten",
          "start": 107.24,
          "end": 108.4,
          "translation": "voted"
        },
        {
          "word": "in",
          "start": 108.4,
          "end": 108.74,
          "translation": "in"
        },
        {
          "word": "New",
          "start": 108.74,
          "end": 109.06,
          "translation": "New"
        },
        {
          "word": "York",
          "start": 109.06,
          "end": 109.46,
          "translation": "York"
        },
        {
          "word": "für",
          "start": 109.46,
          "end": 109.88,
          "translation": "for"
        },
        {
          "word": "eine",
          "start": 109.88,
          "end": 110.3,
          "translation": "one"
        },
        {
          "word": "entsprechende",
          "start": 110.3,
          "end": 111.36,
          "translation": "corresponding"
        },
        {
          "word": "Resolution.",
          "start": 111.36,
          "end": 112.44,
          "translation": "Resolution."
        },
        {
          "word": "Die",
          "start": 113.38,
          "end": 113.76,
          "translation": "The"
        },
        {
          "word": "Veto-Mächte",
          "start": 113.76,
          "end": 115.3,
          "translation": "Veto powers"
        },
        {
          "word": "Russland",
          "start": 115.3,
          "end": 115.76,
          "translation": "Russia"
        },
        {
          "word": "und",
          "start": 115.76,
          "end": 116.24,
          "translation": "and"
        },
        {
          "word": "China",
          "start": 116.24,
          "end": 116.66,
          "translation": "China"
        },
        {
          "word": "enthielten",
          "start": 116.66,
          "end": 117.86,
          "translation": "contained"
        },
        {
          "word": "sich.",
          "start": 117.86,
          "end": 118.22,
          "translation": "itself."
        },
        {
          "word": "Seit",
          "start": 119.16,
          "end": 119.5,
          "translation": "Since"
        },
        {
          "word": "Beginn",
          "start": 119.5,
          "end": 120.14,
          "translation": "Start"
        },
        {
          "word": "des",
          "start": 120.14,
          "end": 120.32,
          "translation": "of the"
        },
        {
          "word": "Krieges",
          "start": 120.32,
          "end": 120.94,
          "translation": "War"
        },
        {
          "word": "Ende",
          "start": 120.94,
          "end": 121.48,
          "translation": "End"
        },
        {
          "word": "Februar",
          "start": 121.48,
          "end": 122.42,
          "translation": "february"
        },
        {
          "word": "sehen",
          "start": 122.42,
          "end": 123.16,
          "translation": "See"
        },
        {
          "word": "sich",
          "start": 123.16,
          "end": 123.66,
          "translation": "itself"
        },
        {
          "word": "die",
          "start": 123.66,
          "end": 123.86,
          "translation": "the"
        },
        {
          "word": "Golfstaaten",
          "start": 123.86,
          "end": 125.44,
          "translation": "Gulf States"
        },
        {
          "word": "Raketen-",
          "start": 125.44,
          "end": 126.02,
          "translation": "Rocket"
        },
        {
          "word": "und",
          "start": 126.02,
          "end": 126.6,
          "translation": "and"
        },
        {
          "word": "Drohnenattacken",
          "start": 126.6,
          "end": 127.92,
          "translation": "Drone attacks"
        },
        {
          "word": "aus",
          "start": 127.92,
          "end": 128.12,
          "translation": "from"
        },
        {
          "word": "dem",
          "start": 128.12,
          "end": 128.38,
          "translation": "the"
        },
        {
          "word": "Iran",
          "start": 128.38,
          "end": 128.88,
          "translation": "Iran"
        },
        {
          "word": "ausgesetzt.",
          "start": 128.88,
          "end": 129.92,
          "translation": "suspended."
        },
        {
          "word": "Diese",
          "start": 129.92,
          "end": 131.04,
          "translation": "These"
        },
        {
          "word": "Angriffe",
          "start": 131.04,
          "end": 131.96,
          "translation": "Attacks"
        },
        {
          "word": "seien",
          "start": 131.96,
          "end": 132.6,
          "translation": "be"
        },
        {
          "word": "völkerrechtswidrig",
          "start": 132.6,
          "end": 134.14,
          "translation": "contrary to international law"
        },
        {
          "word": "und",
          "start": 134.14,
          "end": 134.94,
          "translation": "and"
        },
        {
          "word": "stellten",
          "start": 134.94,
          "end": 135.68,
          "translation": "presented"
        },
        {
          "word": "eine",
          "start": 135.68,
          "end": 136.14,
          "translation": "one"
        },
        {
          "word": "„ernste",
          "start": 136.14,
          "end": 137.12,
          "translation": "\"serious"
        },
        {
          "word": "Bedrohung",
          "start": 137.12,
          "end": 137.9,
          "translation": "Threat"
        },
        {
          "word": "für",
          "start": 137.9,
          "end": 138.1,
          "translation": "for"
        },
        {
          "word": "den",
          "start": 138.1,
          "end": 138.34,
          "translation": "the"
        },
        {
          "word": "weltweiten",
          "start": 138.34,
          "end": 139.12,
          "translation": "worldwide"
        },
        {
          "word": "Frieden",
          "start": 139.12,
          "end": 139.82,
          "translation": "Peace"
        },
        {
          "word": "und",
          "start": 139.82,
          "end": 140.0,
          "translation": "and"
        },
        {
          "word": "die",
          "start": 140.0,
          "end": 140.22,
          "translation": "the"
        },
        {
          "word": "Sicherheit“",
          "start": 140.22,
          "end": 140.78,
          "translation": "Security\""
        },
        {
          "word": "dar,",
          "start": 140.78,
          "end": 142.02,
          "translation": "represent,"
        },
        {
          "word": "heißt",
          "start": 142.02,
          "end": 142.14,
          "translation": "means"
        },
        {
          "word": "es",
          "start": 142.14,
          "end": 142.56,
          "translation": "it"
        },
        {
          "word": "in",
          "start": 142.56,
          "end": 142.8,
          "translation": "in"
        },
        {
          "word": "der",
          "start": 142.8,
          "end": 143.02,
          "translation": "the"
        },
        {
          "word": "Resolution.",
          "start": 143.02,
          "end": 143.98,
          "translation": "Resolution."
        }
      ]
    },
    {
      "isHeadline": true,
      "text": "G7 will Schifffahrt durch Straße von Hormus absichern",
      "words": [
        {
          "word": "G7",
          "start": 147.48,
          "end": 148.76,
          "translation": "G7"
        },
        {
          "word": "will",
          "start": 148.76,
          "end": 149.26,
          "translation": "wants"
        },
        {
          "word": "Schifffahrt",
          "start": 149.26,
          "end": 150.18,
          "translation": "Shipping"
        },
        {
          "word": "durch",
          "start": 150.18,
          "end": 150.4,
          "translation": "through"
        },
        {
          "word": "Straße",
          "start": 150.4,
          "end": 151.02,
          "translation": "Street"
        },
        {
          "word": "von",
          "start": 151.02,
          "end": 151.46,
          "translation": "from"
        },
        {
          "word": "Hormus",
          "start": 151.46,
          "end": 152.14,
          "translation": "Hormuz"
        },
        {
          "word": "absichern",
          "start": 152.14,
          "end": 153.26,
          "translation": "secure"
        }
      ]
    },
    {
      "isHeadline": false,
      "text": "Die Gruppe der sieben großen demokratischen Industrienationen will den Seeweg zum Persischen Golf wieder befahrbar machen. Die G7-Staaten prüfen einen Geleitschutz für Handelsschiffe in der Straße von Hormus. Um solche Eskorten durch Kriegsschiffe zu gewährleisten, sei eine mehrwöchige Vorarbeit nötig, sagte Frankreichs Präsident Emmanuel Macron. Er äußerte sich nach einer Videokonferenz der Staats- und Regierungschefs der G7 zu den wirtschaftlichen Folgen des Iran-Kriegs. Ziel sei die Wiederherstellung der freien Schifffahrt, sobald die Sicherheitslage dies zulasse, so Macron. Die derzeit von iranischen Streitkräften blockierte Meerenge zwischen der Arabischen Halbinsel und dem Iran gilt als eine der wichtigsten Routen im Welthandel.",
      "words": [
        {
          "word": "Die",
          "start": 153.72,
          "end": 154.32,
          "translation": "The"
        },
        {
          "word": "Gruppe",
          "start": 154.32,
          "end": 154.84,
          "translation": "Group"
        },
        {
          "word": "der",
          "start": 154.84,
          "end": 155.18,
          "translation": "the"
        },
        {
          "word": "sieben",
          "start": 155.18,
          "end": 155.74,
          "translation": "seven"
        },
        {
          "word": "großen",
          "start": 155.74,
          "end": 156.32,
          "translation": "large"
        },
        {
          "word": "demokratischen",
          "start": 156.32,
          "end": 157.58,
          "translation": "democratic"
        },
        {
          "word": "Industrienationen",
          "start": 157.58,
          "end": 159.6,
          "translation": "Industrialized nations"
        },
        {
          "word": "will",
          "start": 159.6,
          "end": 159.94,
          "translation": "wants"
        },
        {
          "word": "den",
          "start": 159.94,
          "end": 160.4,
          "translation": "the"
        },
        {
          "word": "Seeweg",
          "start": 160.4,
          "end": 161.08,
          "translation": "Sea route"
        },
        {
          "word": "zum",
          "start": 161.08,
          "end": 161.54,
          "translation": "to the"
        },
        {
          "word": "Persischen",
          "start": 161.54,
          "end": 162.34,
          "translation": "Persian"
        },
        {
          "word": "Golf",
          "start": 162.34,
          "end": 162.7,
          "translation": "Golf"
        },
        {
          "word": "wieder",
          "start": 162.7,
          "end": 163.36,
          "translation": "again"
        },
        {
          "word": "befahrbar",
          "start": 163.36,
          "end": 164.34,
          "translation": "passable"
        },
        {
          "word": "machen.",
          "start": 164.34,
          "end": 164.88,
          "translation": "make."
        },
        {
          "word": "Die",
          "start": 165.5,
          "end": 165.9,
          "translation": "The"
        },
        {
          "word": "G7-Staaten",
          "start": 165.9,
          "end": 167.36,
          "translation": "G7 countries"
        },
        {
          "word": "prüfen",
          "start": 167.36,
          "end": 167.98,
          "translation": "check"
        },
        {
          "word": "einen",
          "start": 167.98,
          "end": 168.62,
          "translation": "one"
        },
        {
          "word": "Geleitschutz",
          "start": 168.62,
          "end": 169.7,
          "translation": "Escort"
        },
        {
          "word": "für",
          "start": 169.7,
          "end": 170.16,
          "translation": "for"
        },
        {
          "word": "Handelsschiffe",
          "start": 170.16,
          "end": 171.38,
          "translation": "Merchant ships"
        },
        {
          "word": "in",
          "start": 171.38,
          "end": 171.76,
          "translation": "in"
        },
        {
          "word": "der",
          "start": 171.76,
          "end": 171.94,
          "translation": "the"
        },
        {
          "word": "Straße",
          "start": 171.94,
          "end": 172.5,
          "translation": "Street"
        },
        {
          "word": "von",
          "start": 172.5,
          "end": 172.86,
          "translation": "from"
        },
        {
          "word": "Hormus.",
          "start": 172.86,
          "end": 173.54,
          "translation": "Hormuz."
        },
        {
          "word": "Um",
          "start": 174.16,
          "end": 174.54,
          "translation": "To"
        },
        {
          "word": "solche",
          "start": 174.54,
          "end": 175.1,
          "translation": "such"
        },
        {
          "word": "Eskorten",
          "start": 175.1,
          "end": 176.0,
          "translation": "Escorts"
        },
        {
          "word": "durch",
          "start": 176.0,
          "end": 176.34,
          "translation": "through"
        },
        {
          "word": "Kriegsschiffe",
          "start": 176.34,
          "end": 177.3,
          "translation": "Warships"
        },
        {
          "word": "zu",
          "start": 177.3,
          "end": 177.6,
          "translation": "to"
        },
        {
          "word": "gewährleisten,",
          "start": 177.6,
          "end": 178.6,
          "translation": "guarantee,"
        },
        {
          "word": "sei",
          "start": 179.14,
          "end": 179.42,
          "translation": "be"
        },
        {
          "word": "eine",
          "start": 179.42,
          "end": 179.94,
          "translation": "one"
        },
        {
          "word": "mehrwöchige",
          "start": 179.94,
          "end": 180.96,
          "translation": "several weeks"
        },
        {
          "word": "Vorarbeit",
          "start": 180.96,
          "end": 181.96,
          "translation": "Preparatory work"
        },
        {
          "word": "nötig,",
          "start": 181.96,
          "end": 182.72,
          "translation": "necessary,"
        },
        {
          "word": "sagte",
          "start": 183.14,
          "end": 183.58,
          "translation": "said"
        },
        {
          "word": "Frankreichs",
          "start": 183.58,
          "end": 184.54,
          "translation": "France"
        },
        {
          "word": "Präsident",
          "start": 184.54,
          "end": 185.0,
          "translation": "President"
        },
        {
          "word": "Emmanuel",
          "start": 185.7,
          "end": 186.14,
          "translation": "Emmanuel"
        },
        {
          "word": "Macron.",
          "start": 186.14,
          "end": 186.92,
          "translation": "Macron."
        },
        {
          "word": "Er",
          "start": 187.84,
          "end": 188.1,
          "translation": "He"
        },
        {
          "word": "äußerte",
          "start": 188.1,
          "end": 188.72,
          "translation": "expressed"
        },
        {
          "word": "sich",
          "start": 188.72,
          "end": 189.18,
          "translation": "itself"
        },
        {
          "word": "nach",
          "start": 189.18,
          "end": 189.46,
          "translation": "to"
        },
        {
          "word": "einer",
          "start": 189.46,
          "end": 189.96,
          "translation": "one"
        },
        {
          "word": "Videokonferenz",
          "start": 189.96,
          "end": 191.4,
          "translation": "Video conference"
        },
        {
          "word": "der",
          "start": 191.4,
          "end": 191.66,
          "translation": "the"
        },
        {
          "word": "Staats-",
          "start": 191.66,
          "end": 192.12,
          "translation": "State"
        },
        {
          "word": "und",
          "start": 192.12,
          "end": 192.66,
          "translation": "and"
        },
        {
          "word": "Regierungschefs",
          "start": 192.66,
          "end": 193.92,
          "translation": "Heads of government"
        },
        {
          "word": "der",
          "start": 193.92,
          "end": 194.2,
          "translation": "the"
        },
        {
          "word": "G7",
          "start": 194.2,
          "end": 194.9,
          "translation": "G7"
        },
        {
          "word": "zu",
          "start": 194.9,
          "end": 195.68,
          "translation": "to"
        },
        {
          "word": "den",
          "start": 195.68,
          "end": 196.08,
          "translation": "the"
        },
        {
          "word": "wirtschaftlichen",
          "start": 196.08,
          "end": 197.16,
          "translation": "economic"
        },
        {
          "word": "Folgen",
          "start": 197.16,
          "end": 197.82,
          "translation": "Consequences"
        },
        {
          "word": "des",
          "start": 197.82,
          "end": 198.24,
          "translation": "of the"
        },
        {
          "word": "Iran-Kriegs.",
          "start": 198.24,
          "end": 200.06,
          "translation": "Iran war."
        },
        {
          "word": "Ziel",
          "start": 200.06,
          "end": 200.6,
          "translation": "Goal"
        },
        {
          "word": "sei",
          "start": 200.6,
          "end": 200.94,
          "translation": "be"
        },
        {
          "word": "die",
          "start": 200.94,
          "end": 201.28,
          "translation": "the"
        },
        {
          "word": "Wiederherstellung",
          "start": 201.28,
          "end": 202.24,
          "translation": "Restoration"
        },
        {
          "word": "der",
          "start": 202.24,
          "end": 202.6,
          "translation": "the"
        },
        {
          "word": "freien",
          "start": 202.6,
          "end": 203.14,
          "translation": "free"
        },
        {
          "word": "Schifffahrt,",
          "start": 203.14,
          "end": 203.96,
          "translation": "Shipping,"
        },
        {
          "word": "sobald",
          "start": 204.3,
          "end": 204.88,
          "translation": "as soon as"
        },
        {
          "word": "die",
          "start": 204.88,
          "end": 205.04,
          "translation": "the"
        },
        {
          "word": "Sicherheitslage",
          "start": 205.04,
          "end": 206.14,
          "translation": "Security situation"
        },
        {
          "word": "dies",
          "start": 206.14,
          "end": 206.6,
          "translation": "this"
        },
        {
          "word": "zulasse,",
          "start": 206.6,
          "end": 207.32,
          "translation": "allow,"
        },
        {
          "word": "so",
          "start": 207.76,
          "end": 207.88,
          "translation": "so"
        },
        {
          "word": "Macron.",
          "start": 207.88,
          "end": 208.48,
          "translation": "Macron."
        },
        {
          "word": "Die",
          "start": 208.48,
          "end": 209.36,
          "translation": "The"
        },
        {
          "word": "derzeit",
          "start": 209.36,
          "end": 210.16,
          "translation": "currently"
        },
        {
          "word": "von",
          "start": 210.16,
          "end": 210.54,
          "translation": "from"
        },
        {
          "word": "iranischen",
          "start": 210.54,
          "end": 211.46,
          "translation": "Iranian"
        },
        {
          "word": "Streitkräften",
          "start": 211.46,
          "end": 212.48,
          "translation": "armed forces"
        },
        {
          "word": "blockierte",
          "start": 212.48,
          "end": 213.18,
          "translation": "blocked"
        },
        {
          "word": "Meerenge",
          "start": 213.18,
          "end": 214.16,
          "translation": "Strait"
        },
        {
          "word": "zwischen",
          "start": 214.16,
          "end": 215.02,
          "translation": "between"
        },
        {
          "word": "der",
          "start": 215.02,
          "end": 215.38,
          "translation": "the"
        },
        {
          "word": "Arabischen",
          "start": 215.38,
          "end": 216.26,
          "translation": "Arabic"
        },
        {
          "word": "Halbinsel",
          "start": 216.26,
          "end": 217.08,
          "translation": "Peninsula"
        },
        {
          "word": "und",
          "start": 217.08,
          "end": 217.42,
          "translation": "and"
        },
        {
          "word": "dem",
          "start": 217.42,
          "end": 217.66,
          "translation": "the"
        },
        {
          "word": "Iran",
          "start": 217.66,
          "end": 218.14,
          "translation": "Iran"
        },
        {
          "word": "gilt",
          "start": 218.14,
          "end": 219.06,
          "translation": "applies"
        },
        {
          "word": "als",
          "start": 219.06,
          "end": 219.56,
          "translation": "as"
        },
        {
          "word": "eine",
          "start": 219.56,
          "end": 219.9,
          "translation": "one"
        },
        {
          "word": "der",
          "start": 219.9,
          "end": 220.16,
          "translation": "the"
        },
        {
          "word": "wichtigsten",
          "start": 220.16,
          "end": 221.04,
          "translation": "most important"
        },
        {
          "word": "Routen",
          "start": 221.04,
          "end": 221.6,
          "translation": "Routes"
        },
        {
          "word": "im",
          "start": 221.6,
          "end": 221.92,
          "translation": "in the"
        },
        {
          "word": "Welthandel.",
          "start": 221.92,
          "end": 223.02,
          "translation": "World trade."
        }
      ]
    },
    {
      "isHeadline": true,
      "text": "Wadephul hat keine Hinweise auf eine Verminung am Persischen Golf",
      "words": [
        {
          "word": "Wadephul",
          "start": 223.02,
          "end": 227.56,
          "translation": "Wadephul"
        },
        {
          "word": "hat",
          "start": 227.56,
          "end": 227.76,
          "translation": "has"
        },
        {
          "word": "keine",
          "start": 227.76,
          "end": 228.28,
          "translation": "none"
        },
        {
          "word": "Hinweise",
          "start": 228.28,
          "end": 229.02,
          "translation": "Notes"
        },
        {
          "word": "auf",
          "start": 229.02,
          "end": 229.5,
          "translation": "on"
        },
        {
          "word": "eine",
          "start": 229.5,
          "end": 229.96,
          "translation": "one"
        },
        {
          "word": "Verminung",
          "start": 229.96,
          "end": 230.8,
          "translation": "Mining"
        },
        {
          "word": "am",
          "start": 230.8,
          "end": 231.24,
          "translation": "on"
        },
        {
          "word": "Persischen",
          "start": 231.24,
          "end": 232.06,
          "translation": "Persian"
        },
        {
          "word": "Golf",
          "start": 232.06,
          "end": 232.4,
          "translation": "Golf"
        }
      ]
    },
    {
      "isHeadline": false,
      "text": "Deutschlands Außenminister Johann Wadephul hat sich zurückhaltend zu einem möglichen Einsatz deutscher Minenräumschiffe in der Straße von Hormus geäußert. Zum jetzigen Zeitpunkt gebe es keine Hinweise darauf, dass das Seegebiet vermint sei, sagte er nach einem Besuch im Golfstaat Katar. Wadephul betonte aber, die Meerenge sei derzeit faktisch blockiert und dies habe erhebliche Auswirkungen auf die weltweite Energieversorgung. Wichtig sei eine diplomatische Lösung der aktuellen, durch den Iran-Krieg ausgelösten Krise, so der Bundesaußenminister.",
      "words": [
        {
          "word": "Deutschlands",
          "start": 233.4,
          "end": 234.24,
          "translation": "Germany"
        },
        {
          "word": "Außenminister",
          "start": 234.24,
          "end": 235.2,
          "translation": "Foreign Minister"
        },
        {
          "word": "Johann",
          "start": 235.2,
          "end": 235.68,
          "translation": "John"
        },
        {
          "word": "Wadephul",
          "start": 235.68,
          "end": 236.86,
          "translation": "Wadephul"
        },
        {
          "word": "hat",
          "start": 236.86,
          "end": 237.4,
          "translation": "has"
        },
        {
          "word": "sich",
          "start": 237.4,
          "end": 237.76,
          "translation": "itself"
        },
        {
          "word": "zurückhaltend",
          "start": 237.76,
          "end": 238.94,
          "translation": "reserved"
        },
        {
          "word": "zu",
          "start": 238.94,
          "end": 239.26,
          "translation": "to"
        },
        {
          "word": "einem",
          "start": 239.26,
          "end": 239.54,
          "translation": "one"
        },
        {
          "word": "möglichen",
          "start": 239.54,
          "end": 240.36,
          "translation": "possible"
        },
        {
          "word": "Einsatz",
          "start": 240.36,
          "end": 240.76,
          "translation": "Use"
        },
        {
          "word": "deutscher",
          "start": 240.76,
          "end": 241.58,
          "translation": "German"
        },
        {
          "word": "Minenräumschiffe",
          "start": 241.58,
          "end": 242.98,
          "translation": "Minesweepers"
        },
        {
          "word": "in",
          "start": 242.98,
          "end": 243.58,
          "translation": "in"
        },
        {
          "word": "der",
          "start": 243.58,
          "end": 243.8,
          "translation": "the"
        },
        {
          "word": "Straße",
          "start": 243.8,
          "end": 244.4,
          "translation": "Street"
        },
        {
          "word": "von",
          "start": 244.4,
          "end": 244.78,
          "translation": "from"
        },
        {
          "word": "Hormus",
          "start": 244.78,
          "end": 245.52,
          "translation": "Hormuz"
        },
        {
          "word": "geäußert.",
          "start": 245.52,
          "end": 246.4,
          "translation": "expressed."
        },
        {
          "word": "Zum",
          "start": 246.78,
          "end": 247.34,
          "translation": "To the"
        },
        {
          "word": "jetzigen",
          "start": 247.34,
          "end": 248.06,
          "translation": "present"
        },
        {
          "word": "Zeitpunkt",
          "start": 248.06,
          "end": 248.8,
          "translation": "Time"
        },
        {
          "word": "gebe",
          "start": 248.8,
          "end": 249.18,
          "translation": "give"
        },
        {
          "word": "es",
          "start": 249.18,
          "end": 249.62,
          "translation": "it"
        },
        {
          "word": "keine",
          "start": 249.62,
          "end": 250.16,
          "translation": "none"
        },
        {
          "word": "Hinweise",
          "start": 250.16,
          "end": 250.94,
          "translation": "Notes"
        },
        {
          "word": "darauf,",
          "start": 250.94,
          "end": 251.44,
          "translation": "on it,"
        },
        {
          "word": "dass",
          "start": 252.08,
          "end": 252.18,
          "translation": "that"
        },
        {
          "word": "das",
          "start": 252.18,
          "end": 252.58,
          "translation": "the"
        },
        {
          "word": "Seegebiet",
          "start": 252.58,
          "end": 253.44,
          "translation": "Sea area"
        },
        {
          "word": "vermint",
          "start": 253.44,
          "end": 253.98,
          "translation": "mined"
        },
        {
          "word": "sei,",
          "start": 253.98,
          "end": 254.46,
          "translation": "be,"
        },
        {
          "word": "sagte",
          "start": 254.94,
          "end": 255.49,
          "translation": "said"
        },
        {
          "word": "er",
          "start": 255.49,
          "end": 255.59,
          "translation": "he"
        },
        {
          "word": "nach",
          "start": 255.59,
          "end": 255.91,
          "translation": "to"
        },
        {
          "word": "einem",
          "start": 255.91,
          "end": 256.41,
          "translation": "one"
        },
        {
          "word": "Besuch",
          "start": 256.41,
          "end": 256.99,
          "translation": "Visit"
        },
        {
          "word": "im",
          "start": 256.99,
          "end": 257.55,
          "translation": "in the"
        },
        {
          "word": "Golfstaat",
          "start": 257.55,
          "end": 258.27,
          "translation": "Gulf state"
        },
        {
          "word": "Katar.",
          "start": 258.27,
          "end": 258.83,
          "translation": "Qatar."
        },
        {
          "word": "Wadephul",
          "start": 258.83,
          "end": 260.69,
          "translation": "Wadephul"
        },
        {
          "word": "betonte",
          "start": 260.69,
          "end": 261.13,
          "translation": "emphasized"
        },
        {
          "word": "aber,",
          "start": 261.13,
          "end": 261.81,
          "translation": "but,"
        },
        {
          "word": "die",
          "start": 262.17,
          "end": 262.45,
          "translation": "the"
        },
        {
          "word": "Meerenge",
          "start": 262.45,
          "end": 263.25,
          "translation": "Strait"
        },
        {
          "word": "sei",
          "start": 263.25,
          "end": 263.61,
          "translation": "be"
        },
        {
          "word": "derzeit",
          "start": 263.61,
          "end": 264.43,
          "translation": "currently"
        },
        {
          "word": "faktisch",
          "start": 264.43,
          "end": 265.11,
          "translation": "factual"
        },
        {
          "word": "blockiert",
          "start": 265.11,
          "end": 265.75,
          "translation": "blocked"
        },
        {
          "word": "und",
          "start": 265.75,
          "end": 266.47,
          "translation": "and"
        },
        {
          "word": "dies",
          "start": 266.47,
          "end": 266.79,
          "translation": "this"
        },
        {
          "word": "habe",
          "start": 266.79,
          "end": 267.21,
          "translation": "have"
        },
        {
          "word": "erhebliche",
          "start": 267.21,
          "end": 268.17,
          "translation": "considerable"
        },
        {
          "word": "Auswirkungen",
          "start": 268.17,
          "end": 269.21,
          "translation": "Effects"
        },
        {
          "word": "auf",
          "start": 269.21,
          "end": 269.57,
          "translation": "on"
        },
        {
          "word": "die",
          "start": 269.57,
          "end": 269.83,
          "translation": "the"
        },
        {
          "word": "weltweite",
          "start": 269.83,
          "end": 270.67,
          "translation": "worldwide"
        },
        {
          "word": "Energieversorgung.",
          "start": 270.67,
          "end": 272.21,
          "translation": "Energy supply."
        },
        {
          "word": "Wichtig",
          "start": 272.75,
          "end": 273.33,
          "translation": "Important"
        },
        {
          "word": "sei",
          "start": 273.33,
          "end": 273.77,
          "translation": "be"
        },
        {
          "word": "eine",
          "start": 273.77,
          "end": 274.25,
          "translation": "one"
        },
        {
          "word": "diplomatische",
          "start": 274.25,
          "end": 275.39,
          "translation": "diplomatic"
        },
        {
          "word": "Lösung",
          "start": 275.39,
          "end": 275.87,
          "translation": "Solution"
        },
        {
          "word": "der",
          "start": 275.87,
          "end": 276.55,
          "translation": "the"
        },
        {
          "word": "aktuellen,",
          "start": 276.55,
          "end": 277.65,
          "translation": "current,"
        },
        {
          "word": "durch",
          "start": 277.65,
          "end": 278.07,
          "translation": "through"
        },
        {
          "word": "den",
          "start": 278.07,
          "end": 278.43,
          "translation": "the"
        },
        {
          "word": "Iran-Krieg",
          "start": 278.43,
          "end": 279.45,
          "translation": "Iran war"
        },
        {
          "word": "ausgelösten",
          "start": 279.45,
          "end": 280.43,
          "translation": "triggered"
        },
        {
          "word": "Krise,",
          "start": 280.43,
          "end": 281.05,
          "translation": "Crisis,"
        },
        {
          "word": "so",
          "start": 281.61,
          "end": 281.75,
          "translation": "so"
        },
        {
          "word": "der",
          "start": 281.75,
          "end": 282.09,
          "translation": "the"
        },
        {
          "word": "Bundesaußenminister.",
          "start": 282.09,
          "end": 283.47,
          "translation": "Federal Foreign Minister."
        }
      ]
    },
    {
      "isHeadline": true,
      "text": "Trump will Teil der US-Ölreserven auf den Markt bringen",
      "words": [
        {
          "word": "Trump",
          "start": 286.11,
          "end": 287.29,
          "translation": "Trump"
        },
        {
          "word": "will",
          "start": 287.29,
          "end": 287.71,
          "translation": "wants"
        },
        {
          "word": "Teil",
          "start": 287.71,
          "end": 288.13,
          "translation": "Part"
        },
        {
          "word": "der",
          "start": 288.13,
          "end": 288.49,
          "translation": "the"
        },
        {
          "word": "US-Ölreserven",
          "start": 288.49,
          "end": 290.21,
          "translation": "US oil reserves"
        },
        {
          "word": "auf",
          "start": 290.21,
          "end": 290.53,
          "translation": "on"
        },
        {
          "word": "den",
          "start": 290.53,
          "end": 290.81,
          "translation": "the"
        },
        {
          "word": "Markt",
          "start": 290.81,
          "end": 291.19,
          "translation": "Market"
        },
        {
          "word": "bringen",
          "start": 291.19,
          "end": 291.61,
          "translation": "bring"
        }
      ]
    },
    {
      "isHeadline": false,
      "text": "Nach Deutschland geben auch die USA aufgrund des Iran-Kriegs ihre strategischen Ölreserven teilweise frei. Präsident Donald Trump will damit den rasant gestiegenen Ölpreis stabilisieren. Die USA, Deutschland und die anderen Mitgliedsländer der Internationalen Energie-Agentur (IEA) hatten zuvor die bislang größte Freigabe ihrer Notfallreserven beschlossen. Nach IEA-Angaben soll dadurch eine Rekordmenge von insgesamt 400 Millionen Fass Rohöl zur Verfügung stehen. Doch auch nach dieser Ankündigung zeichnet sich noch keine Entspannung auf den internationalen Ölmärkten ab. Nach Berichten über Angriffe auf Tanker in der Golfregion und die Schließung von Ölterminals schossen die Rohölpreise sogar um neun Prozent nach oben – auf über 100 Dollar je Fass, was einer Menge von 159 Litern entspricht.",
      "words": [
        {
          "word": "Nach",
          "start": 292.39,
          "end": 292.77,
          "translation": "After"
        },
        {
          "word": "Deutschland",
          "start": 292.77,
          "end": 293.49,
          "translation": "Germany"
        },
        {
          "word": "geben",
          "start": 293.49,
          "end": 293.97,
          "translation": "give"
        },
        {
          "word": "auch",
          "start": 293.97,
          "end": 294.47,
          "translation": "also"
        },
        {
          "word": "die",
          "start": 294.47,
          "end": 294.77,
          "translation": "the"
        },
        {
          "word": "USA",
          "start": 294.77,
          "end": 295.43,
          "translation": "USA"
        },
        {
          "word": "aufgrund",
          "start": 295.43,
          "end": 296.29,
          "translation": "due to"
        },
        {
          "word": "des",
          "start": 296.29,
          "end": 296.67,
          "translation": "of the"
        },
        {
          "word": "Iran-Kriegs",
          "start": 296.67,
          "end": 297.75,
          "translation": "Iran war"
        },
        {
          "word": "ihre",
          "start": 297.75,
          "end": 298.41,
          "translation": "their"
        },
        {
          "word": "strategischen",
          "start": 298.41,
          "end": 299.51,
          "translation": "strategic"
        },
        {
          "word": "Ölreserven",
          "start": 299.51,
          "end": 300.65,
          "translation": "Oil reserves"
        },
        {
          "word": "teilweise",
          "start": 300.65,
          "end": 301.51,
          "translation": "Partly"
        },
        {
          "word": "frei.",
          "start": 301.51,
          "end": 302.01,
          "translation": "free."
        },
        {
          "word": "Präsident",
          "start": 302.63,
          "end": 303.25,
          "translation": "President"
        },
        {
          "word": "Donald",
          "start": 303.25,
          "end": 303.85,
          "translation": "Donald"
        },
        {
          "word": "Trump",
          "start": 303.85,
          "end": 304.43,
          "translation": "Trump"
        },
        {
          "word": "will",
          "start": 304.43,
          "end": 305.05,
          "translation": "wants"
        },
        {
          "word": "damit",
          "start": 305.05,
          "end": 305.53,
          "translation": "so that"
        },
        {
          "word": "den",
          "start": 305.53,
          "end": 306.03,
          "translation": "the"
        },
        {
          "word": "rasant",
          "start": 306.03,
          "end": 306.55,
          "translation": "racy"
        },
        {
          "word": "gestiegenen",
          "start": 306.55,
          "end": 307.77,
          "translation": "increased"
        },
        {
          "word": "Ölpreis",
          "start": 307.77,
          "end": 308.59,
          "translation": "Oil price"
        },
        {
          "word": "stabilisieren.",
          "start": 308.59,
          "end": 309.79,
          "translation": "stabilize."
        },
        {
          "word": "Die",
          "start": 309.99,
          "end": 310.63,
          "translation": "The"
        },
        {
          "word": "USA,",
          "start": 310.63,
          "end": 311.45,
          "translation": "USA,"
        },
        {
          "word": "Deutschland",
          "start": 311.93,
          "end": 312.63,
          "translation": "Germany"
        },
        {
          "word": "und",
          "start": 312.63,
          "end": 313.31,
          "translation": "and"
        },
        {
          "word": "die",
          "start": 313.31,
          "end": 313.63,
          "translation": "the"
        },
        {
          "word": "anderen",
          "start": 313.63,
          "end": 314.17,
          "translation": "other"
        },
        {
          "word": "Mitgliedsländer",
          "start": 314.17,
          "end": 315.35,
          "translation": "Member countries"
        },
        {
          "word": "der",
          "start": 315.35,
          "end": 315.83,
          "translation": "the"
        },
        {
          "word": "Internationalen",
          "start": 315.83,
          "end": 317.27,
          "translation": "International"
        },
        {
          "word": "Energie-Agentur",
          "start": 317.27,
          "end": 318.69,
          "translation": "Energy Agency"
        },
        {
          "word": "(IEA)",
          "start": 318.69,
          "end": 319.93,
          "translation": "(IEA)"
        },
        {
          "word": "hatten",
          "start": 319.93,
          "end": 320.83,
          "translation": "had"
        },
        {
          "word": "zuvor",
          "start": 320.83,
          "end": 321.67,
          "translation": "before"
        },
        {
          "word": "die",
          "start": 321.67,
          "end": 322.01,
          "translation": "the"
        },
        {
          "word": "bislang",
          "start": 322.01,
          "end": 322.51,
          "translation": "so far"
        },
        {
          "word": "größte",
          "start": 322.51,
          "end": 323.23,
          "translation": "largest"
        },
        {
          "word": "Freigabe",
          "start": 323.23,
          "end": 323.97,
          "translation": "Release"
        },
        {
          "word": "ihrer",
          "start": 323.97,
          "end": 324.53,
          "translation": "their"
        },
        {
          "word": "Notfallreserven",
          "start": 324.53,
          "end": 325.77,
          "translation": "Emergency reserves"
        },
        {
          "word": "beschlossen.",
          "start": 325.77,
          "end": 326.27,
          "translation": "decided."
        },
        {
          "word": "Nach",
          "start": 326.93,
          "end": 327.27,
          "translation": "After"
        },
        {
          "word": "IEA-Angaben",
          "start": 327.27,
          "end": 329.21,
          "translation": "IEA data"
        },
        {
          "word": "soll",
          "start": 329.21,
          "end": 329.81,
          "translation": "should"
        },
        {
          "word": "dadurch",
          "start": 329.81,
          "end": 330.35,
          "translation": "thereby"
        },
        {
          "word": "eine",
          "start": 330.35,
          "end": 330.87,
          "translation": "one"
        },
        {
          "word": "Rekordmenge",
          "start": 330.87,
          "end": 331.85,
          "translation": "Record quantity"
        },
        {
          "word": "von",
          "start": 331.85,
          "end": 332.37,
          "translation": "from"
        },
        {
          "word": "insgesamt",
          "start": 332.37,
          "end": 333.17,
          "translation": "in total"
        },
        {
          "word": "400",
          "start": 333.17,
          "end": 334.15,
          "translation": "400"
        },
        {
          "word": "Millionen",
          "start": 334.15,
          "end": 334.69,
          "translation": "million"
        },
        {
          "word": "Fass",
          "start": 334.69,
          "end": 335.33,
          "translation": "Barrel"
        },
        {
          "word": "Rohöl",
          "start": 335.33,
          "end": 336.31,
          "translation": "Crude oil"
        },
        {
          "word": "zur",
          "start": 336.31,
          "end": 336.51,
          "translation": "to the"
        },
        {
          "word": "Verfügung",
          "start": 336.51,
          "end": 336.97,
          "translation": "Disposition"
        },
        {
          "word": "stehen.",
          "start": 336.97,
          "end": 337.61,
          "translation": "stand."
        },
        {
          "word": "Doch",
          "start": 337.97,
          "end": 338.45,
          "translation": "But"
        },
        {
          "word": "auch",
          "start": 338.45,
          "end": 338.99,
          "translation": "also"
        },
        {
          "word": "nach",
          "start": 338.99,
          "end": 339.37,
          "translation": "to"
        },
        {
          "word": "dieser",
          "start": 339.37,
          "end": 339.85,
          "translation": "this"
        },
        {
          "word": "Ankündigung",
          "start": 339.85,
          "end": 340.73,
          "translation": "Announcement"
        },
        {
          "word": "zeichnet",
          "start": 340.73,
          "end": 341.63,
          "translation": "characterizes"
        },
        {
          "word": "sich",
          "start": 341.63,
          "end": 341.99,
          "translation": "itself"
        },
        {
          "word": "noch",
          "start": 341.99,
          "end": 342.19,
          "translation": "still"
        },
        {
          "word": "keine",
          "start": 342.19,
          "end": 342.69,
          "translation": "none"
        },
        {
          "word": "Entspannung",
          "start": 342.69,
          "end": 343.59,
          "translation": "Relaxation"
        },
        {
          "word": "auf",
          "start": 343.59,
          "end": 343.87,
          "translation": "on"
        },
        {
          "word": "den",
          "start": 343.87,
          "end": 344.09,
          "translation": "the"
        },
        {
          "word": "internationalen",
          "start": 344.09,
          "end": 345.53,
          "translation": "international"
        },
        {
          "word": "Ölmärkten",
          "start": 345.53,
          "end": 346.31,
          "translation": "Oil markets"
        },
        {
          "word": "ab.",
          "start": 346.31,
          "end": 346.59,
          "translation": "from."
        },
        {
          "word": "Nach",
          "start": 347.15,
          "end": 347.63,
          "translation": "After"
        },
        {
          "word": "Berichten",
          "start": 347.63,
          "end": 348.33,
          "translation": "Reports"
        },
        {
          "word": "über",
          "start": 348.33,
          "end": 348.89,
          "translation": "about"
        },
        {
          "word": "Angriffe",
          "start": 348.89,
          "end": 349.67,
          "translation": "Attacks"
        },
        {
          "word": "auf",
          "start": 349.67,
          "end": 350.09,
          "translation": "on"
        },
        {
          "word": "Tanker",
          "start": 350.09,
          "end": 350.67,
          "translation": "Tanker"
        },
        {
          "word": "in",
          "start": 350.67,
          "end": 350.89,
          "translation": "in"
        },
        {
          "word": "der",
          "start": 350.89,
          "end": 351.07,
          "translation": "the"
        },
        {
          "word": "Golfregion",
          "start": 351.07,
          "end": 352.01,
          "translation": "Gulf region"
        },
        {
          "word": "und",
          "start": 352.01,
          "end": 352.75,
          "translation": "and"
        },
        {
          "word": "die",
          "start": 352.75,
          "end": 353.05,
          "translation": "the"
        },
        {
          "word": "Schließung",
          "start": 353.05,
          "end": 353.65,
          "translation": "Closure"
        },
        {
          "word": "von",
          "start": 353.65,
          "end": 353.97,
          "translation": "from"
        },
        {
          "word": "Ölterminals",
          "start": 353.97,
          "end": 355.09,
          "translation": "Oil terminals"
        },
        {
          "word": "schossen",
          "start": 355.09,
          "end": 356.01,
          "translation": "shot"
        },
        {
          "word": "die",
          "start": 356.01,
          "end": 356.37,
          "translation": "the"
        },
        {
          "word": "Rohölpreise",
          "start": 356.37,
          "end": 357.61,
          "translation": "Crude oil prices"
        },
        {
          "word": "sogar",
          "start": 357.61,
          "end": 358.07,
          "translation": "even"
        },
        {
          "word": "um",
          "start": 358.07,
          "end": 358.53,
          "translation": "to"
        },
        {
          "word": "neun",
          "start": 358.53,
          "end": 358.87,
          "translation": "nine"
        },
        {
          "word": "Prozent",
          "start": 358.87,
          "end": 359.45,
          "translation": "Percent"
        },
        {
          "word": "nach",
          "start": 359.45,
          "end": 359.93,
          "translation": "to"
        },
        {
          "word": "oben",
          "start": 359.93,
          "end": 360.45,
          "translation": "top"
        },
        {
          "word": "–",
          "start": 360.45,
          "end": 360.45,
          "translation": "-"
        },
        {
          "word": "auf",
          "start": 360.45,
          "end": 361.11,
          "translation": "on"
        },
        {
          "word": "über",
          "start": 361.11,
          "end": 361.65,
          "translation": "about"
        },
        {
          "word": "100",
          "start": 361.65,
          "end": 362.37,
          "translation": "100"
        },
        {
          "word": "Dollar",
          "start": 362.37,
          "end": 362.85,
          "translation": "Dollar"
        },
        {
          "word": "je",
          "start": 362.85,
          "end": 363.21,
          "translation": "each"
        },
        {
          "word": "Fass,",
          "start": 363.21,
          "end": 364.01,
          "translation": "Barrel,"
        },
        {
          "word": "was",
          "start": 364.01,
          "end": 364.31,
          "translation": "what"
        },
        {
          "word": "einer",
          "start": 364.31,
          "end": 364.71,
          "translation": "one"
        },
        {
          "word": "Menge",
          "start": 364.71,
          "end": 365.07,
          "translation": "Quantity"
        },
        {
          "word": "von",
          "start": 365.07,
          "end": 365.47,
          "translation": "from"
        },
        {
          "word": "159",
          "start": 365.47,
          "end": 367.39,
          "translation": "159"
        },
        {
          "word": "Litern",
          "start": 367.39,
          "end": 367.83,
          "translation": "Liters"
        },
        {
          "word": "entspricht.",
          "start": 367.83,
          "end": 368.57,
          "translation": "corresponds."
        }
      ]
    },
    {
      "isHeadline": true,
      "text": "Merz reist nach Oslo – Raumfahrtprojekte sind ein Thema",
      "words": [
        {
          "word": "Merz",
          "start": 368.57,
          "end": 372.55,
          "translation": "Merz"
        },
        {
          "word": "reist",
          "start": 372.55,
          "end": 373.03,
          "translation": "travels"
        },
        {
          "word": "nach",
          "start": 373.03,
          "end": 373.27,
          "translation": "to"
        },
        {
          "word": "Oslo",
          "start": 373.27,
          "end": 373.85,
          "translation": "Oslo"
        },
        {
          "word": "–",
          "start": 373.85,
          "end": 374.65,
          "translation": "-"
        },
        {
          "word": "Raumfahrtprojekte",
          "start": 374.65,
          "end": 375.63,
          "translation": "Space projects"
        },
        {
          "word": "sind",
          "start": 375.63,
          "end": 375.95,
          "translation": "are"
        },
        {
          "word": "ein",
          "start": 375.95,
          "end": 376.33,
          "translation": "a"
        },
        {
          "word": "Thema",
          "start": 376.33,
          "end": 376.77,
          "translation": "Topic"
        }
      ]
    },
    {
      "isHeadline": false,
      "text": "Bundeskanzler Friedrich Merz bricht an diesem Donnerstag zu einer zweitägigen Reise nach Norwegen auf. Geplant ist zunächst ein Treffen von Deutschlands Regierungschef mit dem norwegischen Ministerpräsidenten Jonas Gahr Störe. Neben Merz reisen auch Verteidigungsminister Boris Pistorius und Forschungsministerin Dorothee Bär in das skandinavische Land. Alle drei werden laut Bundesregierung an einem Runden Tisch zur Weltraumkooperation teilnehmen. Am Freitag besuchen Merz und Pistorius die NATO-Übung „Cold Response“, an der in diesem Jahr 11.800 Soldaten von Heer, Marine und Luftwaffe teilnehmen – darunter 1600 Soldaten der Bundeswehr.",
      "words": [
        {
          "word": "Bundeskanzler",
          "start": 377.91,
          "end": 378.81,
          "translation": "Federal Chancellor"
        },
        {
          "word": "Friedrich",
          "start": 378.81,
          "end": 379.41,
          "translation": "Frederick"
        },
        {
          "word": "Merz",
          "start": 379.41,
          "end": 379.89,
          "translation": "Merz"
        },
        {
          "word": "bricht",
          "start": 379.89,
          "end": 380.29,
          "translation": "breaks"
        },
        {
          "word": "an",
          "start": 380.29,
          "end": 380.49,
          "translation": "on"
        },
        {
          "word": "diesem",
          "start": 380.49,
          "end": 380.85,
          "translation": "this"
        },
        {
          "word": "Donnerstag",
          "start": 380.85,
          "end": 381.65,
          "translation": "Thursday"
        },
        {
          "word": "zu",
          "start": 381.65,
          "end": 382.03,
          "translation": "to"
        },
        {
          "word": "einer",
          "start": 382.03,
          "end": 382.33,
          "translation": "one"
        },
        {
          "word": "zweitägigen",
          "start": 382.33,
          "end": 383.35,
          "translation": "two-day"
        },
        {
          "word": "Reise",
          "start": 383.35,
          "end": 383.89,
          "translation": "Journey"
        },
        {
          "word": "nach",
          "start": 383.89,
          "end": 384.23,
          "translation": "to"
        },
        {
          "word": "Norwegen",
          "start": 384.23,
          "end": 384.89,
          "translation": "Norway"
        },
        {
          "word": "auf.",
          "start": 384.89,
          "end": 385.31,
          "translation": "on."
        },
        {
          "word": "Geplant",
          "start": 386.09,
          "end": 386.61,
          "translation": "Planned"
        },
        {
          "word": "ist",
          "start": 386.61,
          "end": 386.99,
          "translation": "is"
        },
        {
          "word": "zunächst",
          "start": 386.99,
          "end": 387.49,
          "translation": "first"
        },
        {
          "word": "ein",
          "start": 387.49,
          "end": 387.97,
          "translation": "a"
        },
        {
          "word": "Treffen",
          "start": 387.97,
          "end": 388.41,
          "translation": "Meeting"
        },
        {
          "word": "von",
          "start": 388.41,
          "end": 388.75,
          "translation": "from"
        },
        {
          "word": "Deutschlands",
          "start": 388.75,
          "end": 389.55,
          "translation": "Germany"
        },
        {
          "word": "Regierungschef",
          "start": 389.55,
          "end": 390.71,
          "translation": "Head of government"
        },
        {
          "word": "mit",
          "start": 390.71,
          "end": 391.29,
          "translation": "with"
        },
        {
          "word": "dem",
          "start": 391.29,
          "end": 391.63,
          "translation": "the"
        },
        {
          "word": "norwegischen",
          "start": 391.63,
          "end": 392.49,
          "translation": "Norwegian"
        },
        {
          "word": "Ministerpräsidenten",
          "start": 392.49,
          "end": 394.21,
          "translation": "Prime Ministers"
        },
        {
          "word": "Jonas",
          "start": 394.21,
          "end": 394.67,
          "translation": "Jonas"
        },
        {
          "word": "Gahr",
          "start": 394.67,
          "end": 395.6,
          "translation": "Gahr"
        },
        {
          "word": "Störe.",
          "start": 395.6,
          "end": 396.53,
          "translation": "Sturgeons."
        },
        {
          "word": "Neben",
          "start": 396.53,
          "end": 396.87,
          "translation": "Besides"
        },
        {
          "word": "Merz",
          "start": 396.87,
          "end": 397.55,
          "translation": "Merz"
        },
        {
          "word": "reisen",
          "start": 397.55,
          "end": 398.03,
          "translation": "travel"
        },
        {
          "word": "auch",
          "start": 398.03,
          "end": 398.39,
          "translation": "also"
        },
        {
          "word": "Verteidigungsminister",
          "start": 398.39,
          "end": 399.87,
          "translation": "Minister of Defense"
        },
        {
          "word": "Boris",
          "start": 399.87,
          "end": 400.43,
          "translation": "Boris"
        },
        {
          "word": "Pistorius",
          "start": 400.43,
          "end": 401.51,
          "translation": "Pistorius"
        },
        {
          "word": "und",
          "start": 401.51,
          "end": 402.13,
          "translation": "and"
        },
        {
          "word": "Forschungsministerin",
          "start": 402.13,
          "end": 403.55,
          "translation": "Research Minister"
        },
        {
          "word": "Dorothee",
          "start": 403.55,
          "end": 404.16,
          "translation": "Dorothee"
        },
        {
          "word": "Bär",
          "start": 404.16,
          "end": 404.77,
          "translation": "Bear"
        },
        {
          "word": "in",
          "start": 404.77,
          "end": 405.07,
          "translation": "in"
        },
        {
          "word": "das",
          "start": 405.07,
          "end": 405.35,
          "translation": "the"
        },
        {
          "word": "skandinavische",
          "start": 405.35,
          "end": 406.33,
          "translation": "Scandinavian"
        },
        {
          "word": "Land.",
          "start": 406.33,
          "end": 406.67,
          "translation": "Country."
        },
        {
          "word": "Alle",
          "start": 407.39,
          "end": 407.77,
          "translation": "All"
        },
        {
          "word": "drei",
          "start": 407.77,
          "end": 408.19,
          "translation": "three"
        },
        {
          "word": "werden",
          "start": 408.19,
          "end": 408.65,
          "translation": "become"
        },
        {
          "word": "laut",
          "start": 408.65,
          "end": 408.97,
          "translation": "according to"
        },
        {
          "word": "Bundesregierung",
          "start": 408.97,
          "end": 409.91,
          "translation": "Federal Government"
        },
        {
          "word": "an",
          "start": 409.91,
          "end": 410.51,
          "translation": "on"
        },
        {
          "word": "einem",
          "start": 410.51,
          "end": 410.83,
          "translation": "one"
        },
        {
          "word": "Runden",
          "start": 410.83,
          "end": 411.27,
          "translation": "Rounds"
        },
        {
          "word": "Tisch",
          "start": 411.27,
          "end": 411.77,
          "translation": "Table"
        },
        {
          "word": "zur",
          "start": 411.77,
          "end": 412.29,
          "translation": "to the"
        },
        {
          "word": "Weltraumkooperation",
          "start": 412.29,
          "end": 413.65,
          "translation": "Space cooperation"
        },
        {
          "word": "teilnehmen.",
          "start": 414.25,
          "end": 414.95,
          "translation": "participate."
        },
        {
          "word": "Am",
          "start": 415.49,
          "end": 416.33,
          "translation": "On"
        },
        {
          "word": "Freitag",
          "start": 416.33,
          "end": 416.97,
          "translation": "Friday"
        },
        {
          "word": "besuchen",
          "start": 416.97,
          "end": 417.55,
          "translation": "visit"
        },
        {
          "word": "Merz",
          "start": 417.55,
          "end": 418.17,
          "translation": "Merz"
        },
        {
          "word": "und",
          "start": 418.17,
          "end": 418.35,
          "translation": "and"
        },
        {
          "word": "Pistorius",
          "start": 418.35,
          "end": 419.27,
          "translation": "Pistorius"
        },
        {
          "word": "die",
          "start": 419.27,
          "end": 419.49,
          "translation": "the"
        },
        {
          "word": "NATO-Übung",
          "start": 419.49,
          "end": 420.41,
          "translation": "NATO exercise"
        },
        {
          "word": "„Cold",
          "start": 420.41,
          "end": 421.07,
          "translation": "\"Cold"
        },
        {
          "word": "Response“,",
          "start": 421.07,
          "end": 421.77,
          "translation": "Response\","
        },
        {
          "word": "an",
          "start": 421.77,
          "end": 422.63,
          "translation": "on"
        },
        {
          "word": "der",
          "start": 422.63,
          "end": 422.89,
          "translation": "the"
        },
        {
          "word": "in",
          "start": 422.89,
          "end": 423.31,
          "translation": "in"
        },
        {
          "word": "diesem",
          "start": 423.31,
          "end": 423.79,
          "translation": "this"
        },
        {
          "word": "Jahr",
          "start": 423.79,
          "end": 424.15,
          "translation": "Year"
        },
        {
          "word": "11.800",
          "start": 424.15,
          "end": 425.75,
          "translation": "11.800"
        },
        {
          "word": "Soldaten",
          "start": 425.75,
          "end": 426.73,
          "translation": "Soldiers"
        },
        {
          "word": "von",
          "start": 426.73,
          "end": 427.19,
          "translation": "from"
        },
        {
          "word": "Heer,",
          "start": 427.19,
          "end": 428.07,
          "translation": "Army,"
        },
        {
          "word": "Marine",
          "start": 428.07,
          "end": 428.33,
          "translation": "Navy"
        },
        {
          "word": "und",
          "start": 428.33,
          "end": 429.01,
          "translation": "and"
        },
        {
          "word": "Luftwaffe",
          "start": 429.01,
          "end": 429.73,
          "translation": "Air Force"
        },
        {
          "word": "teilnehmen",
          "start": 429.73,
          "end": 430.41,
          "translation": "participate"
        },
        {
          "word": "–",
          "start": 430.41,
          "end": 430.89,
          "translation": "-"
        },
        {
          "word": "darunter",
          "start": 430.89,
          "end": 431.27,
          "translation": "including"
        },
        {
          "word": "1600",
          "start": 431.27,
          "end": 432.71,
          "translation": "1600"
        },
        {
          "word": "Soldaten",
          "start": 432.71,
          "end": 433.55,
          "translation": "Soldiers"
        },
        {
          "word": "der",
          "start": 433.55,
          "end": 433.89,
          "translation": "the"
        },
        {
          "word": "Bundeswehr.",
          "start": 433.89,
          "end": 434.69,
          "translation": "German Armed Forces."
        }
      ]
    }
  ]
}